pyfylo/__init__.py
pyfylo/userapi.py
pyfylo/pypack/fylo/commandprocessor.cp36-win_amd64.pyd
pyfylo/pypack/fylo/config.cp36-win_amd64.pyd
pyfylo/pypack/fylo/controlserver.cp36-win_amd64.pyd
pyfylo/pypack/fylo/mavlink.cp36-win_amd64.pyd
pyfylo/pypack/fylo/msganalyzer.cp36-win_amd64.pyd
pyfylo/pypack/fylo/stateprocessor.cp36-win_amd64.pyd
pyfylo/pypack/fylo/taskprocessor.cp36-win_amd64.pyd
pyfylo/pypack/fylo/uwb.cp36-win_amd64.pyd
pyfylo/pypack/system/buffer.cp36-win_amd64.pyd
pyfylo/pypack/system/command.cp36-win_amd64.pyd
pyfylo/pypack/system/communicationcontroller.cp36-win_amd64.pyd
pyfylo/pypack/system/communicationcontrollerfactory.cp36-win_amd64.pyd
pyfylo/pypack/system/dancecontroller.cp36-win_amd64.pyd
pyfylo/pypack/system/dancefileanalyzer.cp36-win_amd64.pyd
pyfylo/pypack/system/datacenter.cp36-win_amd64.pyd
pyfylo/pypack/system/dispatcher.cp36-win_amd64.pyd
pyfylo/pypack/system/firmwareanalyzer.cp36-win_amd64.pyd
pyfylo/pypack/system/logcenter.cp36-win_amd64.pyd
pyfylo/pypack/system/mavcrc.cp36-win_amd64.pyd
pyfylo/pypack/system/network.cp36-win_amd64.pyd
pyfylo/pypack/system/networkcontroller.cp36-win_amd64.pyd
pyfylo/pypack/system/serialcontroller.cp36-win_amd64.pyd
pyfylo/pypack/system/state.cp36-win_amd64.pyd
pyfylo/pypack/system/system.cp36-win_amd64.pyd
pyfylo/pypack/system/taskcontroller.cp36-win_amd64.pyd
pyfylo/pypack/system/dance/action_funtion.cp36-win_amd64.pyd
pyfylo/pypack/system/dance/arrow-anticlockwise.matxt
pyfylo/pypack/system/dance/arrow-circle.matxt
pyfylo/pypack/system/dance/arrow-clockwise.matxt
pyfylo/pypack/system/dance/arrow-land.matxt
pyfylo/pypack/system/dance/arrow-shuriken.matxt
pyfylo/pypack/system/dance/arrow-square.matxt
pyfylo/pypack/system/dance/circle-anticlockwise.matxt
pyfylo/pypack/system/dance/circle-arrow.matxt
pyfylo/pypack/system/dance/circle-clockwise.matxt
pyfylo/pypack/system/dance/circle-land.matxt
pyfylo/pypack/system/dance/circle-shuriken.matxt
pyfylo/pypack/system/dance/circle-square.matxt
pyfylo-2.2.4.dist-info/METADATA
pyfylo-2.2.4.dist-info/WHEEL
pyfylo-2.2.4.dist-info/top_level.txt
pyfylo-2.2.4.dist-info/RECORD
