Metadata-Version: 2.1
Name: pyfylo
Version: 2.2.4
Summary: Fylo Edu package
Home-page: UNKNOWN
Author: HighGreat
Author-email: highgreat@hg-fly.com
License: UNKNOWN
Platform: UNKNOWN
Classifier: Intended Audience :: Education
Classifier: Development Status :: 2 - Pre-Alpha
Classifier: Programming Language :: Python
Classifier: Programming Language :: Python :: 3
Classifier: Programming Language :: Python :: 3.6
Classifier: Programming Language :: Python :: 3 :: Only
Classifier: Operating System :: Microsoft :: Windows
Requires-Python: >=3.6
Requires-Dist: pyserial (==3.4)
